CHANGES.txt
MANIFEST.in
README.txt
setup.py
collective/__init__.py
collective.local.addgroup.egg-info/PKG-INFO
collective.local.addgroup.egg-info/SOURCES.txt
collective.local.addgroup.egg-info/dependency_links.txt
collective.local.addgroup.egg-info/namespace_packages.txt
collective.local.addgroup.egg-info/not-zip-safe
collective.local.addgroup.egg-info/requires.txt
collective.local.addgroup.egg-info/top_level.txt
collective/local/__init__.py
collective/local/addgroup/__init__.py
collective/local/addgroup/addgroup.gif
collective/local/addgroup/addgrouptolist.py
collective/local/addgroup/addgrouptolist.zcml
collective/local/addgroup/configure.zcml
collective/local/addgroup/delgroup.gif
collective/local/addgroup/dexterity.zcml
collective/local/addgroup/event.py
collective/local/addgroup/extender.py
collective/local/addgroup/interfaces.py
collective/local/addgroup/members.py
collective/local/addgroup/minimal.zcml
collective/local/addgroup/testing.py
collective/local/addgroup/usergroups_groupdetails.pt
collective/local/addgroup/vocabulary.py
collective/local/addgroup/locales/addgroup-manual.pot
collective/local/addgroup/locales/addgroup.pot
collective/local/addgroup/locales/update.sh
collective/local/addgroup/locales/fr/LC_MESSAGES/addgroup.po
collective/local/addgroup/templates/managegroups.pt
collective/local/addgroup/templates/managemembers.pt
collective/local/addgroup/tests/__init__.py
collective/local/addgroup/tests/test_newgroup.py