Metadata-Version: 1.1
Name: collective.local.addgroup
Version: 1.2
Summary: Allows to create a group from the sharing tab. By Ecreall
Home-page: http://svn.plone.org/svn/collective/collective.local.addgroup
Author: Vincent Fretin
Author-email: vincent.fretin@gmail.com
License: GPL
Platform: UNKNOWN
Classifier: Framework :: Plone
Classifier: Programming Language :: Python
